HISTORY.rst
LICENSE
MANIFEST.in
README.rst
requirements.txt
setup.py
pensolvetools/__about__.py
pensolvetools/__init__.py
pensolvetools/functions.py
pensolvetools.egg-info/PKG-INFO
pensolvetools.egg-info/SOURCES.txt
pensolvetools.egg-info/dependency_links.txt
pensolvetools.egg-info/not-zip-safe
pensolvetools.egg-info/requires.txt
pensolvetools.egg-info/top_level.txt