Metadata-Version: 2.1
Name: pensolvetools
Version: 0.0.11
Summary: Additional functions for Pensolve's conversion from Excel to Python code
Home-page: https://github.com/pensolve/pensolvetools
Author: Maxim Millen
Author-email: maxim@pensolve.com
License: MIT
Keywords: pensolve
Platform: UNKNOWN
Classifier: Development Status :: 4 - Beta
Classifier: Intended Audience :: Science/Research
Classifier: Topic :: Scientific/Engineering
Classifier: License :: OSI Approved :: MIT License
Classifier: Programming Language :: Python :: 3
Requires-Python: >=3
Provides-Extra: test
License-File: LICENSE
